form_lib/__init__.py
form_lib/formation.py
TII_formation_package-0.0.2.dist-info/LICENCE
TII_formation_package-0.0.2.dist-info/METADATA
TII_formation_package-0.0.2.dist-info/WHEEL
TII_formation_package-0.0.2.dist-info/top_level.txt
TII_formation_package-0.0.2.dist-info/RECORD
