Metadata-Version: 2.1
Name: TII-formation-package
Version: 0.0.2
Summary: A package to control the drones' formation 
Author-email: Dina Ahmim <dina.ahmim@tii.ae>, Agata Barcis <agata.barcis@tii.ae>
Project-URL: Homepage, https://bitbucket.org/autonomouscv/flight_formation
Classifier: Programming Language :: Python :: 3
Classifier: License :: OSI Approved :: MIT License
Classifier: Operating System :: OS Independent
Requires-Python: >=3.7
License-File: LICENCE
